<?xml version="1.0" encoding="utf-8"?>
<!DOCTYPE hibernate-mapping PUBLIC "-//Hibernate/Hibernate Mapping DTD 3.0//EN"
"http://hibernate.sourceforge.net/hibernate-mapping-3.0.dtd">
<!-- 
    Mapping file autogenerated by MyEclipse Persistence Tools
-->
<hibernate-mapping>
    <class name="cn.yufu.posp.usermanager.domain.model.OaConsoleMenu" table="CONSOLE_MENU" >
        <composite-id name="id" class="cn.yufu.posp.usermanager.domain.model.OaConsoleMenuId">
            <key-property name="menuId" type="java.lang.String">
                <column name="MENU_ID" length="8" />
            </key-property>
            <key-property name="menuName" type="java.lang.String">
                <column name="MENU_NAME" length="40" />
            </key-property>
            <key-property name="menuUrl" type="java.lang.String">
                <column name="MENU_URL" length="200" />
            </key-property>
            <key-property name="menuSort" type="java.lang.Long">
                <column name="MENU_SORT" precision="6" scale="0" />
            </key-property>
            <key-property name="menuParentId" type="java.lang.String">
                <column name="MENU_PARENT_ID" length="8" />
            </key-property>
            <key-property name="menuType" type="java.lang.String">
                <column name="MENU_TYPE" length="1" />
            </key-property>
            <key-property name="menuSysId" type="java.lang.String">
                <column name="MENU_SYS_ID" length="1" />
            </key-property>
        </composite-id>
    </class>
</hibernate-mapping>
