<?xml version="1.0" encoding="utf-8"?>
<!DOCTYPE hibernate-mapping PUBLIC "-//Hibernate/Hibernate Mapping DTD 3.0//EN"
"http://hibernate.sourceforge.net/hibernate-mapping-3.0.dtd">
<!-- 
    Mapping file autogenerated by MyEclipse Persistence Tools
-->
<hibernate-mapping>
    <class name="cn.yufu.posp.terminalmanager.domain.model.SysIssuInst" table="SYS_ISSU_INST" >
        <id name="issuId" type="java.lang.String">
            <column name="ISSU_ID" length="8" />
            <generator class="assigned" />
        </id>
        <property name="issuName" type="java.lang.String">
            <column name="ISSU_NAME" length="100" not-null="true" />
        </property>
        <property name="statFlag" type="java.math.BigDecimal">
            <column name="STAT_FLAG" precision="22" scale="0" not-null="true" />
        </property>
    </class>
</hibernate-mapping>
